disutils/EventHandler.py
disutils/InviteTracker.py
disutils/Music.py
disutils/Pagination.py
disutils/Select.py
disutils/__init__.py
disutils-1.4.32.post2.dist-info/LICENSE.txt
disutils-1.4.32.post2.dist-info/METADATA
disutils-1.4.32.post2.dist-info/WHEEL
disutils-1.4.32.post2.dist-info/top_level.txt
disutils-1.4.32.post2.dist-info/RECORD
