Metadata-Version: 2.1
Name: disutils
Version: 1.4.32.post2
Summary: disutils is a very useful library made to be used with discord.py
Home-page: https://github.com/pintermor9/disutils/
Author: pintermor9
License: UNKNOWN
Platform: UNKNOWN
Classifier: Programming Language :: Python :: 3
Classifier: License :: OSI Approved :: MIT License
Classifier: Operating System :: OS Independent
Requires-Python: >= 3.6
Provides-Extra: docs
Provides-Extra: voice
